Hardware/blocks/tb/32-bit_adder.v
// Code generated by Icestudio 0.8.0
// Thu, 10 Feb 2022 22:03:40 GMT

`default_nettype none

//---- Top entity
module add (
 input [32:1] a,
 input [32:1] b,
 input carry,
 output [32:1] c,
 output [0:7] vinit
);
 wire w0;
 wire [0:31] w1;
 wire [0:31] w2;
 wire [0:31] w3;
 assign w0 = carry;
 assign w1 = a;
 assign w2 = b;
 assign c = w3;
 main_vf6510f vf6510f (
  .sub(w0),
  .b(w1),
  .a(w2),
  .out(w3)
 );
 assign vinit = 8'b00000000;
endmodule

/*-------------------------------------------------*/
/*--   */
/*-- - - - - - - - - - - - - - - - - - - - - - - --*/
/*-- 
/*-------------------------------------------------*/

module main_vf6510f (
 input [32:1] a,
 input [32:1] b,
 input sub,
 output [32:1] out
);
 assign out = a + b + sub;
endmodule

Hardware/blocks/tb/testbench_tb.v
`timescale 1 ns / 100 ps

module and_tb();
	reg[32:1]	a = 0;
	reg[32:1]	b = 0;
	
	reg carry = 0;
	
	wire[32:1] c;
	
	localparam duration = 10000;
	
	always begin
		#41.667
		assign a = 32'b11111111111111111111111111111111;
		assign b = 32'b11111111111111111111111111111111;
	end
	
	add uut(
		.a(a),
		.b(b),
		.c(c)
	);
	
	initial begin
		$dumpfile("testbench_tb.vcd");
		$dumpvars(0, and_tb);
		
		#(duration)
		
		$display("Done!");
		$finish;
	end
	
endmodule

Hardware/blocks/tb/and_tb.vcd
$date
	Thu Feb 10 17:08:02 2022
$end
$version
	Icarus Verilog
$end
$timescale
	1ps
$end
$scope module and_tb $end
$var wire 32 ! c [32:1] $end
$var reg 32 " a [32:1] $end
$var reg 32 # b [32:1] $end
$var reg 1 $ carry $end
$scope module uut $end
$var wire 32 % a [32:1] $end
$var wire 32 & b [32:1] $end
$var wire 32 ' c [32:1] $end
$var wire 1 $ carry $end
$var wire 8 ( vinit [0:7] $end
$var wire 1 ) w0 $end
$var wire 32 * w1 [0:31] $end
$var wire 32 + w2 [0:31] $end
$var wire 32 , w3 [0:31] $end
$scope module vf6510f $end
$var wire 32 - a [32:1] $end
$var wire 32 . b [32:1] $end
$var wire 1 ) sub $end
$var wire 32 / out [32:1] $end
$upscope $end
$upscope $end
$upscope $end
$enddefinitions $end
#0
$dumpvars
b0 /
b0 .
b0 -
b0 ,
b0 +
b0 *
0)
b0 (
b0 '
b0 &
b0 %
0$
b0 #
b0 "
b0 !
$end
#41700
b10 +
b10 -
b10 #
b10 &
b11 !
b11 '
b11 ,
b11 /
b1 *
b1 .
b1 "
b1 %
#83400
b100 +
b100 -
b100 #
b100 &
b110 !
b110 '
b110 ,
b110 /
b10 *
b10 .
b10 "
b10 %
#125100
b110 +
b110 -
b110 #
b110 &
b1001 !
b1001 '
b1001 ,
b1001 /
b11 *
b11 .
b11 "
b11 %
#166800
b1000 +
b1000 -
b1000 #
b1000 &
b1100 !
b1100 '
b1100 ,
b1100 /
b100 *
b100 .
b100 "
b100 %
#208500
b1010 +
b1010 -
b1010 #
b1010 &
b1111 !
b1111 '
b1111 ,
b1111 /
b101 *
b101 .
b101 "
b101 %
#250200
b1100 +
b1100 -
b1100 #
b1100 &
b10010 !
b10010 '
b10010 ,
b10010 /
b110 *
b110 .
b110 "
b110 %
#291900
b1110 +
b1110 -
b1110 #
b1110 &
b10101 !
b10101 '
b10101 ,
b10101 /
b111 *
b111 .
b111 "
b111 %
#333600
b10000 +
b10000 -
b10000 #
b10000 &
b11000 !
b11000 '
b11000 ,
b11000 /
b1000 *
b1000 .
b1000 "
b1000 %
#375300
b10010 +
b10010 -
b10010 #
b10010 &
b11011 !
b11011 '
b11011 ,
b11011 /
b1001 *
b1001 .
b1001 "
b1001 %
#417000
b10100 +
b10100 -
b10100 #
b10100 &
b11110 !
b11110 '
b11110 ,
b11110 /
b1010 *
b1010 .
b1010 "
b1010 %
#458700
b10110 +
b10110 -
b10110 #
b10110 &
b100001 !
b100001 '
b100001 ,
b100001 /
b1011 *
b1011 .
b1011 "
b1011 %
#500400
b11000 +
b11000 -
b11000 #
b11000 &
b100100 !
b100100 '
b100100 ,
b100100 /
b1100 *
b1100 .
b1100 "
b1100 %
#542100
b11010 +
b11010 -
b11010 #
b11010 &
b100111 !
b100111 '
b100111 ,
b100111 /
b1101 *
b1101 .
b1101 "
b1101 %
#583800
b11100 +
b11100 -
b11100 #
b11100 &
b101010 !
b101010 '
b101010 ,
b101010 /
b1110 *
b1110 .
b1110 "
b1110 %
#625500
b11110 +
b11110 -
b11110 #
b11110 &
b101101 !
b101101 '
b101101 ,
b101101 /
b1111 *
b1111 .
b1111 "
b1111 %
#667200
b100000 +
b100000 -
b100000 #
b100000 &
b110000 !
b110000 '
b110000 ,
b110000 /
b10000 *
b10000 .
b10000 "
b10000 %
#708900
b100010 +
b100010 -
b100010 #
b100010 &
b110011 !
b110011 '
b110011 ,
b110011 /
b10001 *
b10001 .
b10001 "
b10001 %
#750600
b100100 +
b100100 -
b100100 #
b100100 &
b110110 !
b110110 '
b110110 ,
b110110 /
b10010 *
b10010 .
b10010 "
b10010 %
#792300
b100110 +
b100110 -
b100110 #
b100110 &
b111001 !
b111001 '
b111001 ,
b111001 /
b10011 *
b10011 .
b10011 "
b10011 %
#834000
b101000 +
b101000 -
b101000 #
b101000 &
b111100 !
b111100 '
b111100 ,
b111100 /
b10100 *
b10100 .
b10100 "
b10100 %
#875700
b101010 +
b101010 -
b101010 #
b101010 &
b111111 !
b111111 '
b111111 ,
b111111 /
b10101 *
b10101 .
b10101 "
b10101 %
#917400
b101100 +
b101100 -
b101100 #
b101100 &
b1000010 !
b1000010 '
b1000010 ,
b1000010 /
b10110 *
b10110 .
b10110 "
b10110 %
#959100
b101110 +
b101110 -
b101110 #
b101110 &
b1000101 !
b1000101 '
b1000101 ,
b1000101 /
b10111 *
b10111 .
b10111 "
b10111 %
#1000800
b110000 +
b110000 -
b110000 #
b110000 &
b1001000 !
b1001000 '
b1001000 ,
b1001000 /
b11000 *
b11000 .
b11000 "
b11000 %
#1042500
b110010 +
b110010 -
b110010 #
b110010 &
b1001011 !
b1001011 '
b1001011 ,
b1001011 /
b11001 *
b11001 .
b11001 "
b11001 %
#1084200
b110100 +
b110100 -
b110100 #
b110100 &
b1001110 !
b1001110 '
b1001110 ,
b1001110 /
b11010 *
b11010 .
b11010 "
b11010 %
#1125900
b110110 +
b110110 -
b110110 #
b110110 &
b1010001 !
b1010001 '
b1010001 ,
b1010001 /
b11011 *
b11011 .
b11011 "
b11011 %
#1167600
b111000 +
b111000 -
b111000 #
b111000 &
b1010100 !
b1010100 '
b1010100 ,
b1010100 /
b11100 *
b11100 .
b11100 "
b11100 %
#1209300
b111010 +
b111010 -
b111010 #
b111010 &
b1010111 !
b1010111 '
b1010111 ,
b1010111 /
b11101 *
b11101 .
b11101 "
b11101 %
#1251000
b111100 +
b111100 -
b111100 #
b111100 &
b1011010 !
b1011010 '
b1011010 ,
b1011010 /
b11110 *
b11110 .
b11110 "
b11110 %
#1292700
b111110 +
b111110 -
b111110 #
b111110 &
b1011101 !
b1011101 '
b1011101 ,
b1011101 /
b11111 *
b11111 .
b11111 "
b11111 %
#1334400
b1000000 +
b1000000 -
b1000000 #
b1000000 &
b1100000 !
b1100000 '
b1100000 ,
b1100000 /
b100000 *
b100000 .
b100000 "
b100000 %
#1376100
b1000010 +
b1000010 -
b1000010 #
b1000010 &
b1100011 !
b1100011 '
b1100011 ,
b1100011 /
b100001 *
b100001 .
b100001 "
b100001 %
#1417800
b1000100 +
b1000100 -
b1000100 #
b1000100 &
b1100110 !
b1100110 '
b1100110 ,
b1100110 /
b100010 *
b100010 .
b100010 "
b100010 %
#1459500
b1000110 +
b1000110 -
b1000110 #
b1000110 &
b1101001 !
b1101001 '
b1101001 ,
b1101001 /
b100011 *
b100011 .
b100011 "
b100011 %
#1501200
b1001000 +
b1001000 -
b1001000 #
b1001000 &
b1101100 !
b1101100 '
b1101100 ,
b1101100 /
b100100 *
b100100 .
b100100 "
b100100 %
#1542900
b1001010 +
b1001010 -
b1001010 #
b1001010 &
b1101111 !
b1101111 '
b1101111 ,
b1101111 /
b100101 *
b100101 .
b100101 "
b100101 %
#1584600
b1001100 +
b1001100 -
b1001100 #
b1001100 &
b1110010 !
b1110010 '
b1110010 ,
b1110010 /
b100110 *
b100110 .
b100110 "
b100110 %
#1626300
b1001110 +
b1001110 -
b1001110 #
b1001110 &
b1110101 !
b1110101 '
b1110101 ,
b1110101 /
b100111 *
b100111 .
b100111 "
b100111 %
#1668000
b1010000 +
b1010000 -
b1010000 #
b1010000 &
b1111000 !
b1111000 '
b1111000 ,
b1111000 /
b101000 *
b101000 .
b101000 "
b101000 %
#1709700
b1010010 +
b1010010 -
b1010010 #
b1010010 &
b1111011 !
b1111011 '
b1111011 ,
b1111011 /
b101001 *
b101001 .
b101001 "
b101001 %
#1751400
b1010100 +
b1010100 -
b1010100 #
b1010100 &
b1111110 !
b1111110 '
b1111110 ,
b1111110 /
b101010 *
b101010 .
b101010 "
b101010 %
#1793100
b1010110 +
b1010110 -
b1010110 #
b1010110 &
b10000001 !
b10000001 '
b10000001 ,
b10000001 /
b101011 *
b101011 .
b101011 "
b101011 %
#1834800
b1011000 +
b1011000 -
b1011000 #
b1011000 &
b10000100 !
b10000100 '
b10000100 ,
b10000100 /
b101100 *
b101100 .
b101100 "
b101100 %
#1876500
b1011010 +
b1011010 -
b1011010 #
b1011010 &
b10000111 !
b10000111 '
b10000111 ,
b10000111 /
b101101 *
b101101 .
b101101 "
b101101 %
#1918200
b1011100 +
b1011100 -
b1011100 #
b1011100 &
b10001010 !
b10001010 '
b10001010 ,
b10001010 /
b101110 *
b101110 .
b101110 "
b101110 %
#1959900
b1011110 +
b1011110 -
b1011110 #
b1011110 &
b10001101 !
b10001101 '
b10001101 ,
b10001101 /
b101111 *
b101111 .
b101111 "
b101111 %
#2001600
b1100000 +
b1100000 -
b1100000 #
b1100000 &
b10010000 !
b10010000 '
b10010000 ,
b10010000 /
b110000 *
b110000 .
b110000 "
b110000 %
#2043300
b1100010 +
b1100010 -
b1100010 #
b1100010 &
b10010011 !
b10010011 '
b10010011 ,
b10010011 /
b110001 *
b110001 .
b110001 "
b110001 %
#2085000
b1100100 +
b1100100 -
b1100100 #
b1100100 &
b10010110 !
b10010110 '
b10010110 ,
b10010110 /
b110010 *
b110010 .
b110010 "
b110010 %
#2126700
b1100110 +
b1100110 -
b1100110 #
b1100110 &
b10011001 !
b10011001 '
b10011001 ,
b10011001 /
b110011 *
b110011 .
b110011 "
b110011 %
#2168400
b1101000 +
b1101000 -
b1101000 #
b1101000 &
b10011100 !
b10011100 '
b10011100 ,
b10011100 /
b110100 *
b110100 .
b110100 "
b110100 %
#2210100
b1101010 +
b1101010 -
b1101010 #
b1101010 &
b10011111 !
b10011111 '
b10011111 ,
b10011111 /
b110101 *
b110101 .
b110101 "
b110101 %
#2251800
b1101100 +
b1101100 -
b1101100 #
b1101100 &
b10100010 !
b10100010 '
b10100010 ,
b10100010 /
b110110 *
b110110 .
b110110 "
b110110 %
#2293500
b1101110 +
b1101110 -
b1101110 #
b1101110 &
b10100101 !
b10100101 '
b10100101 ,
b10100101 /
b110111 *
b110111 .
b110111 "
b110111 %
#2335200
b1110000 +
b1110000 -
b1110000 #
b1110000 &
b10101000 !
b10101000 '
b10101000 ,
b10101000 /
b111000 *
b111000 .
b111000 "
b111000 %
#2376900
b1110010 +
b1110010 -
b1110010 #
b1110010 &
b10101011 !
b10101011 '
b10101011 ,
b10101011 /
b111001 *
b111001 .
b111001 "
b111001 %
#2418600
b1110100 +
b1110100 -
b1110100 #
b1110100 &
b10101110 !
b10101110 '
b10101110 ,
b10101110 /
b111010 *
b111010 .
b111010 "
b111010 %
#2460300
b1110110 +
b1110110 -
b1110110 #
b1110110 &
b10110001 !
b10110001 '
b10110001 ,
b10110001 /
b111011 *
b111011 .
b111011 "
b111011 %
#2502000
b1111000 +
b1111000 -
b1111000 #
b1111000 &
b10110100 !
b10110100 '
b10110100 ,
b10110100 /
b111100 *
b111100 .
b111100 "
b111100 %
#2543700
b1111010 +
b1111010 -
b1111010 #
b1111010 &
b10110111 !
b10110111 '
b10110111 ,
b10110111 /
b111101 *
b111101 .
b111101 "
b111101 %
#2585400
b1111100 +
b1111100 -
b1111100 #
b1111100 &
b10111010 !
b10111010 '
b10111010 ,
b10111010 /
b111110 *
b111110 .
b111110 "
b111110 %
#2627100
b1111110 +
b1111110 -
b1111110 #
b1111110 &
b10111101 !
b10111101 '
b10111101 ,
b10111101 /
b111111 *
b111111 .
b111111 "
b111111 %
#2668800
b10000000 +
b10000000 -
b10000000 #
b10000000 &
b11000000 !
b11000000 '
b11000000 ,
b11000000 /
b1000000 *
b1000000 .
b1000000 "
b1000000 %
#2710500
b10000010 +
b10000010 -
b10000010 #
b10000010 &
b11000011 !
b11000011 '
b11000011 ,
b11000011 /
b1000001 *
b1000001 .
b1000001 "
b1000001 %
#2752200
b10000100 +
b10000100 -
b10000100 #
b10000100 &
b11000110 !
b11000110 '
b11000110 ,
b11000110 /
b1000010 *
b1000010 .
b1000010 "
b1000010 %
#2793900
b10000110 +
b10000110 -
b10000110 #
b10000110 &
b11001001 !
b11001001 '
b11001001 ,
b11001001 /
b1000011 *
b1000011 .
b1000011 "
b1000011 %
#2835600
b10001000 +
b10001000 -
b10001000 #
b10001000 &
b11001100 !
b11001100 '
b11001100 ,
b11001100 /
b1000100 *
b1000100 .
b1000100 "
b1000100 %
#2877300
b10001010 +
b10001010 -
b10001010 #
b10001010 &
b11001111 !
b11001111 '
b11001111 ,
b11001111 /
b1000101 *
b1000101 .
b1000101 "
b1000101 %
#2919000
b10001100 +
b10001100 -
b10001100 #
b10001100 &
b11010010 !
b11010010 '
b11010010 ,
b11010010 /
b1000110 *
b1000110 .
b1000110 "
b1000110 %
#2960700
b10001110 +
b10001110 -
b10001110 #
b10001110 &
b11010101 !
b11010101 '
b11010101 ,
b11010101 /
b1000111 *
b1000111 .
b1000111 "
b1000111 %
#3002400
b10010000 +
b10010000 -
b10010000 #
b10010000 &
b11011000 !
b11011000 '
b11011000 ,
b11011000 /
b1001000 *
b1001000 .
b1001000 "
b1001000 %
#3044100
b10010010 +
b10010010 -
b10010010 #
b10010010 &
b11011011 !
b11011011 '
b11011011 ,
b11011011 /
b1001001 *
b1001001 .
b1001001 "
b1001001 %
#3085800
b10010100 +
b10010100 -
b10010100 #
b10010100 &
b11011110 !
b11011110 '
b11011110 ,
b11011110 /
b1001010 *
b1001010 .
b1001010 "
b1001010 %
#3127500
b10010110 +
b10010110 -
b10010110 #
b10010110 &
b11100001 !
b11100001 '
b11100001 ,
b11100001 /
b1001011 *
b1001011 .
b1001011 "
b1001011 %
#3169200
b10011000 +
b10011000 -
b10011000 #
b10011000 &
b11100100 !
b11100100 '
b11100100 ,
b11100100 /
b1001100 *
b1001100 .
b1001100 "
b1001100 %
#3210900
b10011010 +
b10011010 -
b10011010 #
b10011010 &
b11100111 !
b11100111 '
b11100111 ,
b11100111 /
b1001101 *
b1001101 .
b1001101 "
b1001101 %
#3252600
b10011100 +
b10011100 -
b10011100 #
b10011100 &
b11101010 !
b11101010 '
b11101010 ,
b11101010 /
b1001110 *
b1001110 .
b1001110 "
b1001110 %
#3294300
b10011110 +
b10011110 -
b10011110 #
b10011110 &
b11101101 !
b11101101 '
b11101101 ,
b11101101 /
b1001111 *
b1001111 .
b1001111 "
b1001111 %
#3336000
b10100000 +
b10100000 -
b10100000 #
b10100000 &
b11110000 !
b11110000 '
b11110000 ,
b11110000 /
b1010000 *
b1010000 .
b1010000 "
b1010000 %
#3377700
b10100010 +
b10100010 -
b10100010 #
b10100010 &
b11110011 !
b11110011 '
b11110011 ,
b11110011 /
b1010001 *
b1010001 .
b1010001 "
b1010001 %
#3419400
b10100100 +
b10100100 -
b10100100 #
b10100100 &
b11110110 !
b11110110 '
b11110110 ,
b11110110 /
b1010010 *
b1010010 .
b1010010 "
b1010010 %
#3461100
b10100110 +
b10100110 -
b10100110 #
b10100110 &
b11111001 !
b11111001 '
b11111001 ,
b11111001 /
b1010011 *
b1010011 .
b1010011 "
b1010011 %
#3502800
b10101000 +
b10101000 -
b10101000 #
b10101000 &
b11111100 !
b11111100 '
b11111100 ,
b11111100 /
b1010100 *
b1010100 .
b1010100 "
b1010100 %
#3544500
b10101010 +
b10101010 -
b10101010 #
b10101010 &
b11111111 !
b11111111 '
b11111111 ,
b11111111 /
b1010101 *
b1010101 .
b1010101 "
b1010101 %
#3586200
b10101100 +
b10101100 -
b10101100 #
b10101100 &
b100000010 !
b100000010 '
b100000010 ,
b100000010 /
b1010110 *
b1010110 .
b1010110 "
b1010110 %
#3627900
b10101110 +
b10101110 -
b10101110 #
b10101110 &
b100000101 !
b100000101 '
b100000101 ,
b100000101 /
b1010111 *
b1010111 .
b1010111 "
b1010111 %
#3669600
b10110000 +
b10110000 -
b10110000 #
b10110000 &
b100001000 !
b100001000 '
b100001000 ,
b100001000 /
b1011000 *
b1011000 .
b1011000 "
b1011000 %
#3711300
b10110010 +
b10110010 -
b10110010 #
b10110010 &
b100001011 !
b100001011 '
b100001011 ,
b100001011 /
b1011001 *
b1011001 .
b1011001 "
b1011001 %
#3753000
b10110100 +
b10110100 -
b10110100 #
b10110100 &
b100001110 !
b100001110 '
b100001110 ,
b100001110 /
b1011010 *
b1011010 .
b1011010 "
b1011010 %
#3794700
b10110110 +
b10110110 -
b10110110 #
b10110110 &
b100010001 !
b100010001 '
b100010001 ,
b100010001 /
b1011011 *
b1011011 .
b1011011 "
b1011011 %
#3836400
b10111000 +
b10111000 -
b10111000 #
b10111000 &
b100010100 !
b100010100 '
b100010100 ,
b100010100 /
b1011100 *
b1011100 .
b1011100 "
b1011100 %
#3878100
b10111010 +
b10111010 -
b10111010 #
b10111010 &
b100010111 !
b100010111 '
b100010111 ,
b100010111 /
b1011101 *
b1011101 .
b1011101 "
b1011101 %
#3919800
b10111100 +
b10111100 -
b10111100 #
b10111100 &
b100011010 !
b100011010 '
b100011010 ,
b100011010 /
b1011110 *
b1011110 .
b1011110 "
b1011110 %
#3961500
b10111110 +
b10111110 -
b10111110 #
b10111110 &
b100011101 !
b100011101 '
b100011101 ,
b100011101 /
b1011111 *
b1011111 .
b1011111 "
b1011111 %
#4003200
b11000000 +
b11000000 -
b11000000 #
b11000000 &
b100100000 !
b100100000 '
b100100000 ,
b100100000 /
b1100000 *
b1100000 .
b1100000 "
b1100000 %
#4044900
b11000010 +
b11000010 -
b11000010 #
b11000010 &
b100100011 !
b100100011 '
b100100011 ,
b100100011 /
b1100001 *
b1100001 .
b1100001 "
b1100001 %
#4086600
b11000100 +
b11000100 -
b11000100 #
b11000100 &
b100100110 !
b100100110 '
b100100110 ,
b100100110 /
b1100010 *
b1100010 .
b1100010 "
b1100010 %
#4128300
b11000110 +
b11000110 -
b11000110 #
b11000110 &
b100101001 !
b100101001 '
b100101001 ,
b100101001 /
b1100011 *
b1100011 .
b1100011 "
b1100011 %
#4170000
b11001000 +
b11001000 -
b11001000 #
b11001000 &
b100101100 !
b100101100 '
b100101100 ,
b100101100 /
b1100100 *
b1100100 .
b1100100 "
b1100100 %
#4211700
b11001010 +
b11001010 -
b11001010 #
b11001010 &
b100101111 !
b100101111 '
b100101111 ,
b100101111 /
b1100101 *
b1100101 .
b1100101 "
b1100101 %
#4253400
b11001100 +
b11001100 -
b11001100 #
b11001100 &
b100110010 !
b100110010 '
b100110010 ,
b100110010 /
b1100110 *
b1100110 .
b1100110 "
b1100110 %
#4295100
b11001110 +
b11001110 -
b11001110 #
b11001110 &
b100110101 !
b100110101 '
b100110101 ,
b100110101 /
b1100111 *
b1100111 .
b1100111 "
b1100111 %
#4336800
b11010000 +
b11010000 -
b11010000 #
b11010000 &
b100111000 !
b100111000 '
b100111000 ,
b100111000 /
b1101000 *
b1101000 .
b1101000 "
b1101000 %
#4378500
b11010010 +
b11010010 -
b11010010 #
b11010010 &
b100111011 !
b100111011 '
b100111011 ,
b100111011 /
b1101001 *
b1101001 .
b1101001 "
b1101001 %
#4420200
b11010100 +
b11010100 -
b11010100 #
b11010100 &
b100111110 !
b100111110 '
b100111110 ,
b100111110 /
b1101010 *
b1101010 .
b1101010 "
b1101010 %
#4461900
b11010110 +
b11010110 -
b11010110 #
b11010110 &
b101000001 !
b101000001 '
b101000001 ,
b101000001 /
b1101011 *
b1101011 .
b1101011 "
b1101011 %
#4503600
b11011000 +
b11011000 -
b11011000 #
b11011000 &
b101000100 !
b101000100 '
b101000100 ,
b101000100 /
b1101100 *
b1101100 .
b1101100 "
b1101100 %
#4545300
b11011010 +
b11011010 -
b11011010 #
b11011010 &
b101000111 !
b101000111 '
b101000111 ,
b101000111 /
b1101101 *
b1101101 .
b1101101 "
b1101101 %
#4587000
b11011100 +
b11011100 -
b11011100 #
b11011100 &
b101001010 !
b101001010 '
b101001010 ,
b101001010 /
b1101110 *
b1101110 .
b1101110 "
b1101110 %
#4628700
b11011110 +
b11011110 -
b11011110 #
b11011110 &
b101001101 !
b101001101 '
b101001101 ,
b101001101 /
b1101111 *
b1101111 .
b1101111 "
b1101111 %
#4670400
b11100000 +
b11100000 -
b11100000 #
b11100000 &
b101010000 !
b101010000 '
b101010000 ,
b101010000 /
b1110000 *
b1110000 .
b1110000 "
b1110000 %
#4712100
b11100010 +
b11100010 -
b11100010 #
b11100010 &
b101010011 !
b101010011 '
b101010011 ,
b101010011 /
b1110001 *
b1110001 .
b1110001 "
b1110001 %
#4753800
b11100100 +
b11100100 -
b11100100 #
b11100100 &
b101010110 !
b101010110 '
b101010110 ,
b101010110 /
b1110010 *
b1110010 .
b1110010 "
b1110010 %
#4795500
b11100110 +
b11100110 -
b11100110 #
b11100110 &
b101011001 !
b101011001 '
b101011001 ,
b101011001 /
b1110011 *
b1110011 .
b1110011 "
b1110011 %
#4837200
b11101000 +
b11101000 -
b11101000 #
b11101000 &
b101011100 !
b101011100 '
b101011100 ,
b101011100 /
b1110100 *
b1110100 .
b1110100 "
b1110100 %
#4878900
b11101010 +
b11101010 -
b11101010 #
b11101010 &
b101011111 !
b101011111 '
b101011111 ,
b101011111 /
b1110101 *
b1110101 .
b1110101 "
b1110101 %
#4920600
b11101100 +
b11101100 -
b11101100 #
b11101100 &
b101100010 !
b101100010 '
b101100010 ,
b101100010 /
b1110110 *
b1110110 .
b1110110 "
b1110110 %
#4962300
b11101110 +
b11101110 -
b11101110 #
b11101110 &
b101100101 !
b101100101 '
b101100101 ,
b101100101 /
b1110111 *
b1110111 .
b1110111 "
b1110111 %
#5004000
b11110000 +
b11110000 -
b11110000 #
b11110000 &
b101101000 !
b101101000 '
b101101000 ,
b101101000 /
b1111000 *
b1111000 .
b1111000 "
b1111000 %
#5045700
b11110010 +
b11110010 -
b11110010 #
b11110010 &
b101101011 !
b101101011 '
b101101011 ,
b101101011 /
b1111001 *
b1111001 .
b1111001 "
b1111001 %
#5087400
b11110100 +
b11110100 -
b11110100 #
b11110100 &
b101101110 !
b101101110 '
b101101110 ,
b101101110 /
b1111010 *
b1111010 .
b1111010 "
b1111010 %
#5129100
b11110110 +
b11110110 -
b11110110 #
b11110110 &
b101110001 !
b101110001 '
b101110001 ,
b101110001 /
b1111011 *
b1111011 .
b1111011 "
b1111011 %
#5170800
b11111000 +
b11111000 -
b11111000 #
b11111000 &
b101110100 !
b101110100 '
b101110100 ,
b101110100 /
b1111100 *
b1111100 .
b1111100 "
b1111100 %
#5212500
b11111010 +
b11111010 -
b11111010 #
b11111010 &
b101110111 !
b101110111 '
b101110111 ,
b101110111 /
b1111101 *
b1111101 .
b1111101 "
b1111101 %
#5254200
b11111100 +
b11111100 -
b11111100 #
b11111100 &
b101111010 !
b101111010 '
b101111010 ,
b101111010 /
b1111110 *
b1111110 .
b1111110 "
b1111110 %
#5295900
b11111110 +
b11111110 -
b11111110 #
b11111110 &
b101111101 !
b101111101 '
b101111101 ,
b101111101 /
b1111111 *
b1111111 .
b1111111 "
b1111111 %
#5337600
b100000000 +
b100000000 -
b100000000 #
b100000000 &
b110000000 !
b110000000 '
b110000000 ,
b110000000 /
b10000000 *
b10000000 .
b10000000 "
b10000000 %
#5379300
b100000010 +
b100000010 -
b100000010 #
b100000010 &
b110000011 !
b110000011 '
b110000011 ,
b110000011 /
b10000001 *
b10000001 .
b10000001 "
b10000001 %
#5421000
b100000100 +
b100000100 -
b100000100 #
b100000100 &
b110000110 !
b110000110 '
b110000110 ,
b110000110 /
b10000010 *
b10000010 .
b10000010 "
b10000010 %
#5462700
b100000110 +
b100000110 -
b100000110 #
b100000110 &
b110001001 !
b110001001 '
b110001001 ,
b110001001 /
b10000011 *
b10000011 .
b10000011 "
b10000011 %
#5504400
b100001000 +
b100001000 -
b100001000 #
b100001000 &
b110001100 !
b110001100 '
b110001100 ,
b110001100 /
b10000100 *
b10000100 .
b10000100 "
b10000100 %
#5546100
b100001010 +
b100001010 -
b100001010 #
b100001010 &
b110001111 !
b110001111 '
b110001111 ,
b110001111 /
b10000101 *
b10000101 .
b10000101 "
b10000101 %
#5587800
b100001100 +
b100001100 -
b100001100 #
b100001100 &
b110010010 !
b110010010 '
b110010010 ,
b110010010 /
b10000110 *
b10000110 .
b10000110 "
b10000110 %
#5629500
b100001110 +
b100001110 -
b100001110 #
b100001110 &
b110010101 !
b110010101 '
b110010101 ,
b110010101 /
b10000111 *
b10000111 .
b10000111 "
b10000111 %
#5671200
b100010000 +
b100010000 -
b100010000 #
b100010000 &
b110011000 !
b110011000 '
b110011000 ,
b110011000 /
b10001000 *
b10001000 .
b10001000 "
b10001000 %
#5712900
b100010010 +
b100010010 -
b100010010 #
b100010010 &
b110011011 !
b110011011 '
b110011011 ,
b110011011 /
b10001001 *
b10001001 .
b10001001 "
b10001001 %
#5754600
b100010100 +
b100010100 -
b100010100 #
b100010100 &
b110011110 !
b110011110 '
b110011110 ,
b110011110 /
b10001010 *
b10001010 .
b10001010 "
b10001010 %
#5796300
b100010110 +
b100010110 -
b100010110 #
b100010110 &
b110100001 !
b110100001 '
b110100001 ,
b110100001 /
b10001011 *
b10001011 .
b10001011 "
b10001011 %
#5838000
b100011000 +
b100011000 -
b100011000 #
b100011000 &
b110100100 !
b110100100 '
b110100100 ,
b110100100 /
b10001100 *
b10001100 .
b10001100 "
b10001100 %
#5879700
b100011010 +
b100011010 -
b100011010 #
b100011010 &
b110100111 !
b110100111 '
b110100111 ,
b110100111 /
b10001101 *
b10001101 .
b10001101 "
b10001101 %
#5921400
b100011100 +
b100011100 -
b100011100 #
b100011100 &
b110101010 !
b110101010 '
b110101010 ,
b110101010 /
b10001110 *
b10001110 .
b10001110 "
b10001110 %
#5963100
b100011110 +
b100011110 -
b100011110 #
b100011110 &
b110101101 !
b110101101 '
b110101101 ,
b110101101 /
b10001111 *
b10001111 .
b10001111 "
b10001111 %
#6004800
b100100000 +
b100100000 -
b100100000 #
b100100000 &
b110110000 !
b110110000 '
b110110000 ,
b110110000 /
b10010000 *
b10010000 .
b10010000 "
b10010000 %
#6046500
b100100010 +
b100100010 -
b100100010 #
b100100010 &
b110110011 !
b110110011 '
b110110011 ,
b110110011 /
b10010001 *
b10010001 .
b10010001 "
b10010001 %
#6088200
b100100100 +
b100100100 -
b100100100 #
b100100100 &
b110110110 !
b110110110 '
b110110110 ,
b110110110 /
b10010010 *
b10010010 .
b10010010 "
b10010010 %
#6129900
b100100110 +
b100100110 -
b100100110 #
b100100110 &
b110111001 !
b110111001 '
b110111001 ,
b110111001 /
b10010011 *
b10010011 .
b10010011 "
b10010011 %
#6171600
b100101000 +
b100101000 -
b100101000 #
b100101000 &
b110111100 !
b110111100 '
b110111100 ,
b110111100 /
b10010100 *
b10010100 .
b10010100 "
b10010100 %
#6213300
b100101010 +
b100101010 -
b100101010 #
b100101010 &
b110111111 !
b110111111 '
b110111111 ,
b110111111 /
b10010101 *
b10010101 .
b10010101 "
b10010101 %
#6255000
b100101100 +
b100101100 -
b100101100 #
b100101100 &
b111000010 !
b111000010 '
b111000010 ,
b111000010 /
b10010110 *
b10010110 .
b10010110 "
b10010110 %
#6296700
b100101110 +
b100101110 -
b100101110 #
b100101110 &
b111000101 !
b111000101 '
b111000101 ,
b111000101 /
b10010111 *
b10010111 .
b10010111 "
b10010111 %
#6338400
b100110000 +
b100110000 -
b100110000 #
b100110000 &
b111001000 !
b111001000 '
b111001000 ,
b111001000 /
b10011000 *
b10011000 .
b10011000 "
b10011000 %
#6380100
b100110010 +
b100110010 -
b100110010 #
b100110010 &
b111001011 !
b111001011 '
b111001011 ,
b111001011 /
b10011001 *
b10011001 .
b10011001 "
b10011001 %
#6421800
b100110100 +
b100110100 -
b100110100 #
b100110100 &
b111001110 !
b111001110 '
b111001110 ,
b111001110 /
b10011010 *
b10011010 .
b10011010 "
b10011010 %
#6463500
b100110110 +
b100110110 -
b100110110 #
b100110110 &
b111010001 !
b111010001 '
b111010001 ,
b111010001 /
b10011011 *
b10011011 .
b10011011 "
b10011011 %
#6505200
b100111000 +
b100111000 -
b100111000 #
b100111000 &
b111010100 !
b111010100 '
b111010100 ,
b111010100 /
b10011100 *
b10011100 .
b10011100 "
b10011100 %
#6546900
b100111010 +
b100111010 -
b100111010 #
b100111010 &
b111010111 !
b111010111 '
b111010111 ,
b111010111 /
b10011101 *
b10011101 .
b10011101 "
b10011101 %
#6588600
b100111100 +
b100111100 -
b100111100 #
b100111100 &
b111011010 !
b111011010 '
b111011010 ,
b111011010 /
b10011110 *
b10011110 .
b10011110 "
b10011110 %
#6630300
b100111110 +
b100111110 -
b100111110 #
b100111110 &
b111011101 !
b111011101 '
b111011101 ,
b111011101 /
b10011111 *
b10011111 .
b10011111 "
b10011111 %
